treeish/__init__.py
treeish/get.py
treeish/layer.py
treeish/set.py
treeish/walk.py
treeish-0.0.6.dist-info/WHEEL
treeish-0.0.6.dist-info/METADATA
treeish-0.0.6.dist-info/RECORD
