Metadata-Version: 2.1
Name: treeish
Version: 0.0.6
Summary: Tree function helpers: set ids, get node from ids, fetch nodes with key
Author: Marcelino G. Veloso III
Author-email: mars@veloso.one
Requires-Python: >=3.10,<4.0
Classifier: Programming Language :: Python :: 3
Classifier: Programming Language :: Python :: 3.10
Classifier: Programming Language :: Python :: 3.11
Requires-Dist: python-dotenv (>=0.21,<0.22)
Requires-Dist: rich (>=12.5,<13.0)
